nomy_data_models/__init__.py
nomy_data_models/models/__init__.py
nomy_data_models/models/base.py
nomy_data_models/models/enriched_trade.py
nomy_data_models/models/enums.py
nomy_data_models/models/market_price.py
nomy_data_models/models/position.py
nomy_data_models/models/position_trade.py
nomy_data_models/models/raw_trade.py
nomy_data_models/models/service_state.py
nomy_data_models/models/trade_base.py
nomy_data_models/models/trade_match.py
nomy_data_models/models/wallet_state.py
nomy_data_models/py_to_rust.py
nomy_data_models/utils/string.py
nomy_data_models-0.35.9.dist-info/LICENSE
nomy_data_models-0.35.9.dist-info/METADATA
nomy_data_models-0.35.9.dist-info/WHEEL
nomy_data_models-0.35.9.dist-info/RECORD
